examples/__init__.py
examples/mnist_keras_INI.py
examples/mnist_keras_brian2.py
examples/mnist_keras_loihi.py
examples/mnist_keras_nest.py
examples/mnist_keras_spiNNaker.py
examples/mnist_keras_spiNNaker_sparse.py
examples/mnist_pytorch_INI.py
examples/resnet_keras_INI.py
snntoolbox/__init__.py
snntoolbox/config_defaults
snntoolbox/bin/__init__.py
snntoolbox/bin/run.py
snntoolbox/bin/utils.py
snntoolbox/bin/gui/__init__.py
snntoolbox/bin/gui/gui.py
snntoolbox/bin/gui/tooltip.py
snntoolbox/conversion/__init__.py
snntoolbox/conversion/utils.py
snntoolbox/datasets/__init__.py
snntoolbox/datasets/utils.py
snntoolbox/datasets/aedat/DVSIterator.py
snntoolbox/datasets/aedat/ImportAedat.py
snntoolbox/datasets/aedat/ImportAedatBasicSourceName.py
snntoolbox/datasets/aedat/ImportAedatDataVersion1or2.py
snntoolbox/datasets/aedat/ImportAedatHeaders.py
snntoolbox/datasets/aedat/__init__.py
snntoolbox/datasets/aedat/avi_to_lmdb.py
snntoolbox/parsing/__init__.py
snntoolbox/parsing/utils.py
snntoolbox/parsing/model_libs/__init__.py
snntoolbox/parsing/model_libs/caffe_input_lib.py
snntoolbox/parsing/model_libs/keras_input_lib.py
snntoolbox/parsing/model_libs/lasagne_input_lib.py
snntoolbox/parsing/model_libs/pytorch_input_lib.py
snntoolbox/simulation/__init__.py
snntoolbox/simulation/plotting.py
snntoolbox/simulation/utils.py
snntoolbox/simulation/backends/__init__.py
snntoolbox/simulation/backends/inisim/__init__.py
snntoolbox/simulation/backends/inisim/temporal_mean_rate_tensorflow.py
snntoolbox/simulation/backends/inisim/temporal_mean_rate_theano.py
snntoolbox/simulation/backends/inisim/temporal_pattern.py
snntoolbox/simulation/backends/inisim/ttfs.py
snntoolbox/simulation/backends/inisim/ttfs_corrective.py
snntoolbox/simulation/backends/inisim/ttfs_dyn_thresh.py
snntoolbox/simulation/backends/megasim/__init__.py
snntoolbox/simulation/backends/megasim/megasim.py
snntoolbox/simulation/target_simulators/INI_temporal_mean_rate_target_sim.py
snntoolbox-0.6.0.dist-info/LICENSE.txt
snntoolbox-0.6.0.dist-info/METADATA
snntoolbox-0.6.0.dist-info/WHEEL
snntoolbox-0.6.0.dist-info/entry_points.txt
snntoolbox-0.6.0.dist-info/top_level.txt
snntoolbox-0.6.0.dist-info/RECORD
