Metadata-Version: 2.1
Name: snntoolbox
Version: 0.6.0
Summary: Spiking neural network conversion toolbox
Home-page: https://github.com/NeuromorphicProcessorProject/snn_toolbox
Author: Bodo Rueckauer
Author-email: bodo.rueckauer@gmail.com
License: MIT
Download-URL: https://github.com/NeuromorphicProcessorProject/snn_toolbox.git
Keywords: neural networks,deep learning,spiking
Platform: UNKNOWN
Classifier: License :: OSI Approved :: MIT License
Classifier: Programming Language :: Python :: 2.7
Classifier: Programming Language :: Python :: 3
Classifier: Programming Language :: Python :: 3.6
Classifier: Programming Language :: Python :: 3.7
Requires-Dist: tensorflow
